thermopack/__init__.py
thermopack/cpa.py
thermopack/cubic.py
thermopack/extended_csp.py
thermopack/lee_kesler.py
thermopack/ljs_bh.py
thermopack/ljs_wca.py
thermopack/multiparameter.py
thermopack/pcsaft.py
thermopack/pets.py
thermopack/platform_specifics.py
thermopack/plotutils.py
thermopack/quantum_cubic.py
thermopack/saft.py
thermopack/saftvrmie.py
thermopack/saftvrqmie.py
thermopack/tcPR.py
thermopack/thermo.py
thermopack/thermopack.dll
thermopack/thermopack_state.py
thermopack/utils.py
thermopack-2.2.3.dist-info/METADATA
thermopack-2.2.3.dist-info/WHEEL
thermopack-2.2.3.dist-info/top_level.txt
thermopack-2.2.3.dist-info/RECORD
