Metadata-Version: 2.1
Name: thermopack
Version: 2.2.3
Summary: Python interface to thermopack
Home-page: https://github.com/thermotools/thermopack
Author: Morten Hammer
Author-email: Morten Hammer <morten.hammer@ntnu.no>
Maintainer-email: Morten Hammer <morten.hammer@ntnu.no>, Vegard Gjeldvik Jervell <vegard.g.jervell@ntnu.no>
Project-URL: Homepage, https://github.com/thermotools/thermopack
Project-URL: Bug Tracker, https://github.com/thermotools/thermopack/issues
Keywords: physics,thermodynamics,equations_of_state,phase_equilibria,SAFT
Classifier: Programming Language :: Python :: 3
Classifier: Programming Language :: Fortran
Classifier: Operating System :: MacOS
Classifier: Operating System :: POSIX :: Linux
Classifier: Operating System :: Microsoft :: Windows
Classifier: License :: OSI Approved :: MIT License
Requires-Python: >=3.6
